{
  "slider": [
    {
      "id": 1,
      "sliderImage": "/images/slider/slider2.jpg",
      "sliderTitle": "Buy with Bitcoins on our Shop",
      "sliderText": "We are providing safest transactions with BitCoin",
      "position": 2
    },
    {
      "id": 2,
      "sliderImage": "/images/slider/slider1.jpeg",
      "sliderTitle": "Our Shop is growing and accessible to everyone",
      "sliderText": "You can buy any item you want with us",
      "position": 1
    }
  ],
  "services": [
    {
      "id": 1,
      "image": "MdSupportAgent",
      "title": "24/7 Support",
      "text": "We will help you anytime, anywhere.",
      "position": 2
    },
    {
      "id": 2,
      "image": "MdShoppingCart",
      "title": "24/7 Shop",
      "text": "Our Shop is always open for you.",
      "position": 2
    },
    {
      "id": 3,
      "image": "MdDeliveryDining",
      "title": "24/7 Service",
      "text": "Our Service is always open.",
      "position": 3
    }
  ]
}